finishline/__init__.py
finishline/bootstrap_components.py
finishline/finishline.py
finishline/grid_components.py
finishline-0.3.0.dist-info/METADATA
finishline-0.3.0.dist-info/WHEEL
finishline-0.3.0.dist-info/top_level.txt
finishline-0.3.0.dist-info/RECORD
