Metadata-Version: 2.1
Name: finishline
Version: 0.3.0
Summary: Framework for Building Beautiful and Functional Dashbords
Home-page: http://github.com/AlgorithmHub/finishline
Maintainer: Alex Cabello
Maintainer-email: alex.cabello@algorithmhub.com
License: MIT
Keywords: dash dashboard ui grid layout
Platform: UNKNOWN
Classifier: Development Status :: 3 - Alpha
Classifier: Intended Audience :: Science/Research
Classifier: Intended Audience :: Developers
Classifier: License :: OSI Approved
Classifier: Programming Language :: Python
Classifier: Topic :: Software Development
Classifier: Topic :: Scientific/Engineering
Classifier: Operating System :: Microsoft :: Windows
Classifier: Operating System :: POSIX
Classifier: Operating System :: Unix
Classifier: Operating System :: MacOS
Classifier: Programming Language :: Python :: 3 :: Only
Requires-Dist: dash (>=0.42.0)
Requires-Dist: dash-responsive-grid-layout (>=0.3.0)
Requires-Dist: dash-building-blocks (>=0.1.2)
